lawnmowerlatte/__init__.py
lawnmowerlatte/__main__.py
lawnmowerlatte/imports.py
lawnmowerlatte/logger.py
lawnmowerlatte/script.py
lawnmowerlatte/scriptgen.py
lawnmowerlatte/util.py
lawnmowerlatte/version.py
lawnmowerlatte/behave/__init__.py
lawnmowerlatte/behave/compose.py
lawnmowerlatte/behave/exceptions.py
lawnmowerlatte/behave/generator.py
lawnmowerlatte/behave/generator_extensions.py
lawnmowerlatte/behave/lexical_analyzer.py
lawnmowerlatte/behave/step_wrappers.py
lawnmowerlatte/behave/threadpp.py
lawnmowerlatte/behave/tools.py
lawnmowerlatte/behave/utils.py
lawnmowerlatte/templates/script.jinja
lawnmowerlatte-1.1.33.dist-info/LICENSE
lawnmowerlatte-1.1.33.dist-info/METADATA
lawnmowerlatte-1.1.33.dist-info/WHEEL
lawnmowerlatte-1.1.33.dist-info/top_level.txt
lawnmowerlatte-1.1.33.dist-info/RECORD
